src/__init__.py
src/main.py
safe_commit-1.0.1.dist-info/METADATA
safe_commit-1.0.1.dist-info/WHEEL
safe_commit-1.0.1.dist-info/entry_points.txt
safe_commit-1.0.1.dist-info/top_level.txt
safe_commit-1.0.1.dist-info/RECORD
