Metadata-Version: 2.1
Name: safe-commit
Version: 1.0.1
Summary: A pre-commit hook for stopping you from committing to the main branch.
Home-page: UNKNOWN
Author: Crawford Collins
License: UNKNOWN
Platform: UNKNOWN
Requires-Python: >=3.8
Requires-Dist: gitpython
